exchange_rates_mariana_drozd
