Metadata-Version: 2.1
Name: exchange-rates-mariana-drozd
Version: 0.0.4
Summary: A small library for getting information on cash exchange rates of PrivatBank and the NBU on the selected date
Home-page: UNKNOWN
Author: Mariana Drozd
Author-email: mariana.drozd.work@gmail.com
License: MIT
Project-URL: Source, https://gtlb.jetsoftpro.com/mariana.drozd/exchange_rates_mariana_drozd
Keywords: python,exchange rate,privatbank
Platform: UNKNOWN
Classifier: Intended Audience :: Education
Classifier: Programming Language :: Python :: 3
Classifier: License :: OSI Approved :: MIT License
Classifier: Operating System :: OS Independent
License-File: LICENSE
